aheadengine/__init__.py
aheadengine/app.py
aheadengine-0.0.3.dist-info/METADATA
aheadengine-0.0.3.dist-info/WHEEL
aheadengine-0.0.3.dist-info/top_level.txt
aheadengine-0.0.3.dist-info/RECORD
