Metadata-Version: 2.4
Name: aheadengine
Version: 0.0.3
Requires-Dist: Flask
